neuronsphere/__init__.py
neuronsphere/neuronsphere.py
neuronsphere-1.0.51.dist-info/METADATA
neuronsphere-1.0.51.dist-info/WHEEL
neuronsphere-1.0.51.dist-info/top_level.txt
neuronsphere-1.0.51.dist-info/RECORD
