Metadata-Version: 2.1
Name: neuronsphere
Version: 1.0.51
Summary: Python bundle for all public NeuronSphere components
Home-page: UNKNOWN
Author: Alex Burgoon
Author-email: alex.burgoon@hmdlabs.io
License: Apache 2.0
Platform: UNKNOWN
Requires-Dist: acachecontrol (==0.3.5)
Requires-Dist: aenum (==3.1.15)
Requires-Dist: aiohappyeyeballs (==2.4.3)
Requires-Dist: aiohttp (==3.10.10)
Requires-Dist: aiosignal (==1.3.1)
Requires-Dist: alembic (==1.13.3)
Requires-Dist: arrow (==1.3.0)
Requires-Dist: async-timeout (==4.0.3)
Requires-Dist: attrs (==24.2.0)
Requires-Dist: aws-requests-auth (==0.4.3)
Requires-Dist: aws-secretsmanager-caching (==1.1.1.5)
Requires-Dist: awscrt (==0.23.10)
Requires-Dist: backoff (==2.2.1)
Requires-Dist: binaryornot (==0.4.4)
Requires-Dist: bleach (==4.1.0)
Requires-Dist: boto3 (==1.36.22)
Requires-Dist: botocore (==1.36.23)
Requires-Dist: build (==1.2.2.post1)
Requires-Dist: cachetools (==5.2.0)
Requires-Dist: cement (==3.0.6)
Requires-Dist: certifi (==2022.12.7)
Requires-Dist: cffi (==1.15.0)
Requires-Dist: cfgv (==3.4.0)
Requires-Dist: chardet (==5.2.0)
Requires-Dist: charset-normalizer (==2.0.12)
Requires-Dist: click (==8.0.4)
Requires-Dist: colorlog (==6.6.0)
Requires-Dist: cookiecutter (==2.6.0)
Requires-Dist: coverage[toml] (==6.3.2)
Requires-Dist: cryptography (==39.0.1)
Requires-Dist: decorator (==5.1.1)
Requires-Dist: deprecated (==1.2.18)
Requires-Dist: distlib (==0.3.9)
Requires-Dist: docker (==7.0.0)
Requires-Dist: docutils (==0.18.1)
Requires-Dist: ecdsa (==0.19.0)
Requires-Dist: filelock (==3.18.0)
Requires-Dist: frozenlist (==1.3.3)
Requires-Dist: gitdb (==4.0.12)
Requires-Dist: gitpython (==3.1.30)
Requires-Dist: google-auth (==2.9.1)
Requires-Dist: greenlet (==1.1.3.post0)
Requires-Dist: gremlinpython (==3.7.2)
Requires-Dist: hmd-cli-app (~=1.2.603)
Requires-Dist: hmd-cli-bartleby (~=1.0.44)
Requires-Dist: hmd-cli-bender (~=0.1.31)
Requires-Dist: hmd-cli-build (~=0.1.63)
Requires-Dist: hmd-cli-configure (~=1.0.42)
Requires-Dist: hmd-cli-docker (~=0.1.158)
Requires-Dist: hmd-cli-explorer (~=0.1.35)
Requires-Dist: hmd-cli-mickey (~=1.0.51)
Requires-Dist: hmd-cli-neuronsphere (~=0.3.152)
Requires-Dist: hmd-cli-python (~=0.2.97)
Requires-Dist: hmd-cli-repo (~=0.3.149)
Requires-Dist: hmd-cli-tools (~=1.2.236)
Requires-Dist: hmd-cli-transform-deploy (~=0.1.71)
Requires-Dist: hmd-entity-storage (~=0.2.268)
Requires-Dist: hmd-graphql-client (~=0.1.119)
Requires-Dist: hmd-lang-deployment (~=0.1.78)
Requires-Dist: hmd-lang-naming (~=0.1.13)
Requires-Dist: hmd-lib-auth (~=0.1.90)
Requires-Dist: hmd-lib-containers (~=0.1.51)
Requires-Dist: hmd-lib-librarian-client (~=0.1.84)
Requires-Dist: hmd-lib-manifest (~=0.1.3)
Requires-Dist: hmd-lib-naming (~=0.2.46)
Requires-Dist: hmd-lib-transform (~=0.1.57)
Requires-Dist: hmd-meta-types (~=0.2.92)
Requires-Dist: hmd-schema-loader (~=0.2.35)
Requires-Dist: id (==1.5.0)
Requires-Dist: identify (==2.6.10)
Requires-Dist: idna (==3.3)
Requires-Dist: importlib-metadata (==8.4.0)
Requires-Dist: iniconfig (==1.1.1)
Requires-Dist: inquirerpy (==0.3.4)
Requires-Dist: isodate (==0.7.2)
Requires-Dist: jeepney (==0.8.0)
Requires-Dist: jinja2 (==3.0.3)
Requires-Dist: jmespath (==0.10.0)
Requires-Dist: jsonschema (==4.23.0)
Requires-Dist: jsonschema-specifications (==2024.10.1)
Requires-Dist: keyring (==23.5.0)
Requires-Dist: kubernetes (==24.2.0)
Requires-Dist: mako (==1.3.6)
Requires-Dist: markdown-it-py (==2.2.0)
Requires-Dist: markupsafe (==3.0.2)
Requires-Dist: mdurl (==0.1.2)
Requires-Dist: multidict (==6.1.0)
Requires-Dist: nest-asyncio (==1.6.0)
Requires-Dist: nodeenv (==1.9.1)
Requires-Dist: oauthlib (==3.2.2)
Requires-Dist: okta-jwt-verifier (==0.2.4)
Requires-Dist: packaging (==24.2)
Requires-Dist: pfzy (==0.3.4)
Requires-Dist: pip-compile-multi (==2.6.3)
Requires-Dist: pip-tools (==7.4.1)
Requires-Dist: platformdirs (==4.3.7)
Requires-Dist: pluggy (==1.0.0)
Requires-Dist: pre-commit (==4.2.0)
Requires-Dist: prompt-toolkit (==3.0.38)
Requires-Dist: psycopg2-binary (==2.9.6)
Requires-Dist: py (==1.11.0)
Requires-Dist: pyasn1 (==0.4.8)
Requires-Dist: pyasn1-modules (==0.2.8)
Requires-Dist: pycparser (==2.21)
Requires-Dist: pydantic (==1.10.5)
Requires-Dist: pygithub (==1.58)
Requires-Dist: pygments (==2.14.0)
Requires-Dist: pyjwt (==2.6.0)
Requires-Dist: pynacl (==1.5.0)
Requires-Dist: pyopenssl (==23.0.0)
Requires-Dist: pyproject-hooks (==1.2.0)
Requires-Dist: pytest (==7.0.1)
Requires-Dist: pytest-cov (==3.0.0)
Requires-Dist: python-dateutil (==2.8.2)
Requires-Dist: python-dotenv (==0.19.2)
Requires-Dist: python-jose (==3.4.0)
Requires-Dist: python-on-whales (==0.68.0)
Requires-Dist: python-slugify (==8.0.4)
Requires-Dist: pyyaml (==6.0.1)
Requires-Dist: readme-renderer (==37.3)
Requires-Dist: referencing (==0.35.1)
Requires-Dist: requests (==2.32.3)
Requires-Dist: requests-oauthlib (==1.3.1)
Requires-Dist: requests-toolbelt (==0.9.1)
Requires-Dist: retry2 (==0.9.5)
Requires-Dist: rfc3986 (==2.0.0)
Requires-Dist: rich (==13.3.5)
Requires-Dist: rpds-py (==0.20.0)
Requires-Dist: rsa (==4.8)
Requires-Dist: s3transfer (==0.11.2)
Requires-Dist: secretstorage (==3.3.3)
Requires-Dist: six (==1.16.0)
Requires-Dist: smmap (==5.0.2)
Requires-Dist: sqlalchemy (==2.0.36)
Requires-Dist: termcolor (==1.1.0)
Requires-Dist: text-unidecode (==1.3)
Requires-Dist: tomli (==2.0.1)
Requires-Dist: toposort (==1.10)
Requires-Dist: tqdm (==4.63.0)
Requires-Dist: twine (==6.1.0)
Requires-Dist: typer (==0.7.0)
Requires-Dist: types-python-dateutil (==2.9.0.20241206)
Requires-Dist: typing-extensions (==4.12.2)
Requires-Dist: urllib3 (==1.26.8)
Requires-Dist: virtualenv (==20.30.0)
Requires-Dist: wcwidth (==0.2.6)
Requires-Dist: webencodings (==0.5.1)
Requires-Dist: websocket-client (==1.3.3)
Requires-Dist: wheel (==0.45.1)
Requires-Dist: wrapt (==1.17.2)
Requires-Dist: yarl (==1.12.0)
Requires-Dist: yaspin (==2.1.0)
Requires-Dist: zipp (==3.15.0)
